README.md
setup.py
input_picker/__init__.py
input_picker/bool.py
input_picker/colors.py
input_picker/common.py
input_picker/list.py
input_picker/obj.py
input_picker.egg-info/PKG-INFO
input_picker.egg-info/SOURCES.txt
input_picker.egg-info/dependency_links.txt
input_picker.egg-info/not-zip-safe
input_picker.egg-info/requires.txt
input_picker.egg-info/top_level.txt