Metadata-Version: 1.0
Name: input-picker
Version: 0.1.1.0
Summary: UNKNOWN
Home-page: https://github.com/Cologler/input-picker-python
Author: cologler
Author-email: skyoflw@gmail.com
License: MIT License
Platform: UNKNOWN
